{
  "printing-press": {
    "binary": "printing-press",
    "binary_absolute": "/Users/moraybrown/go/bin/printing-press",
    "version": "4.2.1",
    "kind": "meta-tool",
    "legal_class": "meta",
    "domain": "cli-generation",
    "lab_only": false,
    "auth_optional": ["GITHUB_TOKEN", "GH_TOKEN"],
    "purpose": "Generates new CLIs for any API on demand. Slash command: /printing-press <api>."
  },
  "company-goat": {
    "binary": "company-goat-pp-cli",
    "binary_absolute": "/Users/moraybrown/go/bin/company-goat-pp-cli",
    "version": "1.0.0",
    "kind": "library-cli",
    "legal_class": "public_api",
    "domain": "company-research",
    "lab_only": false,
    "sources": [
      "SEC EDGAR Form D",
      "GitHub",
      "Hacker News (Algolia)",
      "Companies House (UK)",
      "Y Combinator directory",
      "Wikidata SPARQL",
      "RDAP / DNS"
    ],
    "auth_optional": ["GITHUB_TOKEN", "COMPANIES_HOUSE_API_KEY"],
    "built_in_sync": true,
    "mirror_table_generic": "pp-mirrors/company-goat.db",
    "agent_flag": "--agent",
    "common_subcommands": [
      "snapshot",
      "funding",
      "funding-trend",
      "engineering",
      "mentions",
      "launches",
      "legal",
      "wiki",
      "yc",
      "domain",
      "signal",
      "sync"
    ]
  },
  "google-places": {
    "binary": "google-places-pp-cli",
    "binary_absolute": "/Users/moraybrown/.local/bin/google-places-pp-cli",
    "source_path": "pp-tools/google-places-pp-cli/cli.mjs",
    "version": "0.1.0",
    "kind": "library-cli",
    "legal_class": "public_api",
    "domain": "place-discovery",
    "lab_only": false,
    "sources": [
      "Google Places API (New) — places.googleapis.com/v1"
    ],
    "auth_required": ["GOOGLE_PLACES_API_KEY"],
    "billing_note": "Requires Google Cloud project with billing enabled. $200/month free credit covers ~6K text searches; pay-per-call above the cap.",
    "agent_flag": "--agent",
    "common_subcommands": [
      "search",
      "nearby",
      "details",
      "autocomplete",
      "doctor"
    ]
  },
  "workday-cxs": {
    "binary": "workday-cxs-pp-cli",
    "binary_absolute": "/Users/moraybrown/.local/bin/workday-cxs-pp-cli",
    "source_path": "pp-tools/workday-cxs-pp-cli/cli.mjs",
    "version": "0.1.0",
    "kind": "library-cli",
    "legal_class": "scraped_endpoint",
    "scope": "PERSONAL_USE_ONLY",
    "domain": "hiring-intel",
    "lab_only": true,
    "sources": [
      "Workday CXS endpoints — {tenant}.{dc}.myworkdayjobs.com/wday/cxs/..."
    ],
    "auth_required": [],
    "legal_note": "Workday's ToS prohibits scraping. Output of this CLI is for personal research only — do NOT redistribute, do NOT ship as a product feature, do NOT crawl aggressively. Sustained heavy use may trigger tenant rate limits or IP blocks. Endpoints are unauthenticated but unstable; tenants can request blocks at any time.",
    "agent_flag": "--agent",
    "common_subcommands": [
      "scan",
      "job",
      "doctor"
    ]
  },
  "reddit": {
    "binary": "reddit-pp-cli",
    "binary_absolute": "/Users/moraybrown/.local/bin/reddit-pp-cli",
    "source_path": "pp-tools/reddit-pp-cli/cli.mjs",
    "version": "0.1.0",
    "kind": "library-cli",
    "legal_class": "public_api",
    "domain": "social-sentiment",
    "lab_only": false,
    "sources": [
      "Reddit OAuth API — oauth.reddit.com (client_credentials grant)"
    ],
    "auth_required": ["REDDIT_CLIENT_ID", "REDDIT_CLIENT_SECRET"],
    "auth_optional": ["REDDIT_USERNAME"],
    "setup_note": "One-time: https://www.reddit.com/prefs/apps → create 'script' type app → copy client_id + client_secret to .env. Reddit closed all unauthenticated .json endpoints in 2023; OAuth is mandatory now.",
    "agent_flag": "--agent",
    "common_subcommands": [
      "search",
      "subreddit",
      "thread",
      "doctor"
    ],
    "token_cache": "~/.cache/reddit-pp-cli/token.json (24h TTL)"
  },
  "ats-surface": {
    "binary": "ats-surface-pp-cli",
    "binary_absolute": "/Users/moraybrown/.local/bin/ats-surface-pp-cli",
    "source_path": "pp-tools/ats-surface-pp-cli/cli.mjs",
    "version": "0.1.0",
    "kind": "library-cli",
    "legal_class": "public_api",
    "domain": "hiring-intel",
    "lab_only": false,
    "sources": [
      "Greenhouse Job Board API",
      "Lever Postings API (v0)",
      "Ashby Public Job Board API",
      "SmartRecruiters Posting API",
      "Workable widget API",
      "Recruitee Careers Site API"
    ],
    "auth_required": [],
    "agent_flag": "--agent",
    "common_subcommands": [
      "scan",
      "list-ats",
      "doctor"
    ],
    "complementary_to": "jobposting-schema (for non-ATS career sites)"
  },
  "jobposting-schema": {
    "binary": "jobposting-schema-pp-cli",
    "binary_absolute": "/Users/moraybrown/.local/bin/jobposting-schema-pp-cli",
    "source_path": "pp-tools/jobposting-schema-pp-cli/cli.mjs",
    "version": "0.1.0",
    "kind": "library-cli",
    "legal_class": "public_structured_data",
    "domain": "job-posting-extraction",
    "lab_only": false,
    "sources": [
      "schema.org JobPosting JSON-LD blocks embedded in public career pages"
    ],
    "auth_required": [],
    "coverage_note": "Works on sites that ship JSON-LD server-side (e.g. USAJobs, government sites, classic-CMS career pages, sites taking Google for Jobs SEO seriously). Many 2026-era SPA career sites (Greenhouse SPA, Stripe, Apple, Microsoft) hydrate JSON-LD client-side and return 0 blocks here — for those, route to ats-surface-pp-cli (when built) or the upstream ATS API directly.",
    "agent_flag": "--agent",
    "common_subcommands": [
      "extract",
      "sitemap",
      "discover",
      "doctor"
    ]
  }
}
